.travis.yml
MANIFEST.in
Makefile
README.rst
bootstrap.py
buildout.cfg
setup.py
docs/CHANGELOG.rst
docs/LICENSE.rst
docs/api.rst
docs/conf.py
docs/glossary.rst
docs/index.rst
redturtle/__init__.py
redturtle/__init__.pyc
redturtle.gritterize.egg-info/PKG-INFO
redturtle.gritterize.egg-info/SOURCES.txt
redturtle.gritterize.egg-info/dependency_links.txt
redturtle.gritterize.egg-info/entry_points.txt
redturtle.gritterize.egg-info/namespace_packages.txt
redturtle.gritterize.egg-info/not-zip-safe
redturtle.gritterize.egg-info/requires.txt
redturtle.gritterize.egg-info/top_level.txt
redturtle/gritterize/__init__.py
redturtle/gritterize/configure.zcml
redturtle/gritterize/interfaces.py
redturtle/gritterize/testing.py
redturtle/gritterize/browser/__init__.py
redturtle/gritterize/browser/configure.zcml
redturtle/gritterize/browser/test-redturtle-gritterize.pt
redturtle/gritterize/browser/static/.gitkeep
redturtle/gritterize/browser/static/js/gritterize.js
redturtle/gritterize/browser/static/styles/gritterize.css
redturtle/gritterize/profiles/default/browserlayer.xml
redturtle/gritterize/profiles/default/cssregistry.xml
redturtle/gritterize/profiles/default/jsregistry.xml
redturtle/gritterize/profiles/default/metadata.xml
redturtle/gritterize/tests/__init__.py
redturtle/gritterize/tests/test_setup.py