Metadata-Version: 1.1
Name: redturtle.gritterize
Version: 0.9.3
Summary: Plone integration with Gritter
Home-page: https://pypi.python.org/pypi/redturtle.gritterize
Author: RedTurtle Technology
Author-email: sviluppoplone@redturtle.it
License: BSD
Keywords: Plone Python
Platform: UNKNOWN
Classifier: Framework :: Plone
Classifier: Programming Language :: Python
Classifier: Programming Language :: Python :: 2.6
Classifier: Programming Language :: Python :: 2.7
Classifier: Framework :: Plone :: 4.0
Classifier: Framework :: Plone :: 4.1
Classifier: Framework :: Plone :: 4.2
Classifier: Framework :: Plone :: 4.3
